PsychoPy-1.85.6.data/data/psychojs.zip
PsychoPy-1.85.6.data/scripts/psychopyApp.py
PsychoPy-1.85.6.data/scripts/psychopy_post_inst.py
PsychoPy-1.85.6.dist-info/DESCRIPTION.rst
PsychoPy-1.85.6.dist-info/METADATA
PsychoPy-1.85.6.dist-info/RECORD
PsychoPy-1.85.6.dist-info/WHEEL
PsychoPy-1.85.6.dist-info/metadata.json
PsychoPy-1.85.6.dist-info/pbr.json
PsychoPy-1.85.6.dist-info/top_level.txt
psychopy/CHANGELOG.txt
psychopy/LICENSE.txt
psychopy/LICENSES.txt
psychopy/__init__.py
psychopy/clock.py
psychopy/colors.py
psychopy/compatibility.py
psychopy/constants.py
psychopy/core.py
psychopy/event.py
psychopy/exceptions.py
psychopy/filters.py
psychopy/gamma.py
psychopy/info.py
psychopy/locale_setup.py
psychopy/logging.py
psychopy/microphone.py
psychopy/misc.py
psychopy/psychojs.zip
psychopy/web.py
psychopy/app/__init__.py
psychopy/app/_psychopyApp.py
psychopy/app/appData.spec
psychopy/app/connections.py
psychopy/app/dialogs.py
psychopy/app/ipythonShell.py
psychopy/app/preferencesDlg.py
psychopy/app/projects.py
psychopy/app/psychopyApp.py
psychopy/app/stdOutRich.py
psychopy/app/urls.py
psychopy/app/utils.py
psychopy/app/Resources/DejaVuSerif.ttf
psychopy/app/Resources/README.txt
psychopy/app/Resources/__init__.py
psychopy/app/Resources/color128.png
psychopy/app/Resources/color16.png
psychopy/app/Resources/color32.png
psychopy/app/Resources/color32a.png
psychopy/app/Resources/compile128.png
psychopy/app/Resources/compile16.png
psychopy/app/Resources/compile32.png
psychopy/app/Resources/filenew128.png
psychopy/app/Resources/filenew16.png
psychopy/app/Resources/filenew32.png
psychopy/app/Resources/fileopen128.png
psychopy/app/Resources/fileopen16.png
psychopy/app/Resources/fileopen32.png
psychopy/app/Resources/filesave128.png
psychopy/app/Resources/filesave16.png
psychopy/app/Resources/filesave32.png
psychopy/app/Resources/filesaveas128.png
psychopy/app/Resources/filesaveas16.png
psychopy/app/Resources/filesaveas32.png
psychopy/app/Resources/monitors128.png
psychopy/app/Resources/monitors16.png
psychopy/app/Resources/monitors32.png
psychopy/app/Resources/preferences128.png
psychopy/app/Resources/preferences16.png
psychopy/app/Resources/preferences32.png
