Metadata-Version: 2.0
Name: PsychoPy
Version: 1.85.6
Summary: Psychophysics toolkit for Python
Home-page: http://www.psychopy.org
Author: Jonathan Peirce
Author-email: psychopy-dev@googlegroups.com
License: GNU GPLv3 (or more recent equivalent)
Download-URL: https://github.com/psychopy/psychopy/releases/
Platform: UNKNOWN
Classifier: Development Status :: 4 - Beta
Classifier: Operating System :: MacOS :: MacOS X
Classifier: Operating System :: Microsoft :: Windows
Classifier: Operating System :: POSIX
Classifier: Programming Language :: Python
Requires-Dist: cffi
Requires-Dist: configobj
Requires-Dist: future
Requires-Dist: gevent
Requires-Dist: json-tricks
Requires-Dist: matplotlib
Requires-Dist: moviepy
Requires-Dist: msgpack-python
Requires-Dist: numpy
Requires-Dist: opencv-python
Requires-Dist: openpyxl
Requires-Dist: pandas
Requires-Dist: pillow
Requires-Dist: psutil
Requires-Dist: pygame
Requires-Dist: pyglet
Requires-Dist: pyobjc-core
Requires-Dist: pyobjc-framework-Quartz
Requires-Dist: pyosf
Requires-Dist: pyparallel
Requires-Dist: pyserial
Requires-Dist: python-bidi
Requires-Dist: pyyaml
Requires-Dist: requests[security]
Requires-Dist: scipy
Requires-Dist: sounddevice
Requires-Dist: soundfile
Requires-Dist: tables
Requires-Dist: wxPython
Requires-Dist: xlrd
